{"Title":"U.S. stocks lower at close of trade; Dow Jones Industrial Average down 0.16%","Date":1460678400000}
{"Title":"U.S. stocks mixed at close of trade; Dow Jones Industrial Average up 0.14%","Date":1468886400000}
{"Title":"Notable earnings after Thursday\u2019s close","Date":1493164800000}
{"Title":"After Hours Gainers \/ Losers","Date":1500508800000}
{"Title":"Notable earnings after Thursday\u2019s close","Date":1508889600000}
{"Title":"After Hours Gainers \/ Losers (08\/21\/2018)","Date":1534809600000}
{"Title":"U.S. stocks mixed at close of trade; Dow Jones Industrial Average down 0.34%","Date":1534896000000}
{"Title":"Apple, Amazon deny Bloomberg report on Chinese hardware attack","Date":1538611200000}
{"Title":"DHS says no reason to doubt firms' China hack denials","Date":1538784000000}
{"Title":"Apple tells Congress it found no signs of hacking attack","Date":1538870400000}
{"Title":"FBI Director deflects questions on Chinese chip investigation","Date":1539129600000}
{"Title":"Tim Cook calls on Bloomberg to retract spy chip story","Date":1539907200000}
{"Title":"Supermicro looks to open second server assembly site in United States","Date":1591228800000}
{"Title":"Northland Securities Stick to Their Buy Rating for Super Micro Computer","Date":1591833600000}
{"Title":"Northland Securities Stick to Their Buy Rating for Super Micro Computer","Date":1592438400000}
{"Title":"Northland Securities Stick to Their Buy Rating for Super Micro Computer","Date":1595548800000}
{"Title":"U.S. SEC charges Super Micro Computer, former CFO with accounting reporting violations","Date":1598313600000}
{"Title":"Northland Securities Stick to Their Buy Rating for Super Micro Computer","Date":1598400000000}
{"Title":"Northland Securities Stick to Their Buy Rating for Super Micro Computer","Date":1600128000000}
{"Title":"Northland Securities Stick to Their Buy Rating for Super Micro Computer","Date":1604361600000}
{"Title":"Susquehanna Stick to Their Buy Rating for Super Micro Computer","Date":1604361600000}
{"Title":"Susquehanna Stick to Their Buy Rating for Super Micro Computer","Date":1612310400000}
{"Title":"Northland Securities Stick to Their Buy Rating for Super Micro Computer","Date":1613433600000}
{"Title":"Northland Securities Stick to Their Buy Rating for Super Micro Computer","Date":1614038400000}
{"Title":"Northland Securities Stick to Their Buy Rating for Super Micro Computer","Date":1614902400000}
{"Title":"Northland Securities Stick to Their Buy Rating for Super Micro Computer","Date":1615852800000}
{"Title":"2 Red-Hot Computer Hardware Stocks to Buy Now","Date":1618185600000}
{"Title":"Susquehanna Stick to Their Buy Rating for Super Micro Computer","Date":1635811200000}
{"Title":"Super Micro Computer Stock Jumps on Raised Q3 Outlook","Date":1650240000000}
{"Title":"After-Hours Stock Movers 04\/18: Super Micro and Griffon Higher; NETGEAR and Acadia Lower (more...)","Date":1650240000000}
{"Title":"Pre-Open Stock Movers 04\/19: Super Micro and American Campus Higher; NETGEAR and Stellantis Lower (more...)","Date":1650326400000}
{"Title":"Super Micro Computer Tops Q3 EPS by 75c; Raises Outlook","Date":1651536000000}
{"Title":"Super Micro Computer Tops Q4 EPS by $1.04","Date":1660003200000}
{"Title":"Cloud hangs over U.S. chipmakers on worries data center growth could slow","Date":1660608000000}
{"Title":"Exclusive-Biden to hit China with broader curbs on U.S. chip and tool exports -sources","Date":1662940800000}
{"Title":"Exclusive-Biden to hit China with broader curbs on U.S. chip and tool exports -sources","Date":1663200000000}
{"Title":"Super Micro Computer receives Investment Bank Analyst Rating Update","Date":1663545600000}
{"Title":"Super Micro Computer Tops Q1 EPS by $1.24, Offers Guidance","Date":1667260800000}
{"Title":"Super Micro Computer Earnings, Revenue Beat in Q1","Date":1667260800000}
{"Title":"Super Micro Computer PT receives Investment Bank Analyst Rating Update","Date":1667347200000}
{"Title":"After-hours movers: Lucid gains on liquidity boost, Entrada Therapeutics sinks on FDA hold","Date":1671408000000}
{"Title":"Super Micro Computer shares tumble on Spruce Point short report","Date":1673308800000}
{"Title":"Super Micro Computer earnings beat by $0.53, revenue topped estimates","Date":1675123200000}
{"Title":"Super Micro Computer Tops Q2 EPS by 53c, Guidance Misses","Date":1675123200000}
{"Title":"Super Micro Computer PT receives Investment Bank Analyst Rating Update","Date":1675209600000}
{"Title":"Super Micro Computer and Rakuten Symphony Extend Their Collaboration and Offer Complete 5G, Telco, and Edge Solutions","Date":1677628800000}
{"Title":"Constellation Brands, Shell,  FedEx rise premarket; Costco falls","Date":1680739200000}
{"Title":"Super Micro Compu receives Investment Bank Analyst Rating Update","Date":1680739200000}
{"Title":"Pure Storage offers best-in-class products, Super Micro Computer expectations at risk - Wedbush","Date":1680739200000}
{"Title":"Super Micro Computer Reports Prelim Q3 Results","Date":1682294400000}
{"Title":"Super Micro Computer Falls 9% After Slashing Guidance","Date":1682294400000}
{"Title":"Super Micro Computer tumbles after cutting Q3 revenue forecast","Date":1682294400000}
{"Title":"Super Micro Computer earnings missed by $0.36, revenue fell short of estimates","Date":1682985600000}
{"Title":"After-hours movers: AMD, Starbucks fall following EPS; Livent gains","Date":1682985600000}
{"Title":"Super Micro Compu receives Investment Bank Analyst Rating Update","Date":1683072000000}
{"Title":"Super Micro Computer Launches NVIDIA HGX H100 8 and 4-GPU H100 Servers with Liquid Cooling","Date":1684713600000}
{"Title":"Super Micro Computer declines despite strong preliminary fourth quarter results","Date":1689811200000}
{"Title":"Super Micro Compu receives Investment Bank Analyst Rating Update","Date":1689897600000}
{"Title":"Super Micro Computer earnings beat by $0.75, revenue topped estimates","Date":1691452800000}
{"Title":"Super Micro Compu receives Investment Bank Analyst Rating Update","Date":1691539200000}
{"Title":"Buy weakness in Nvidia stock - Citi","Date":1691625600000}
{"Title":"Super Micro Compu receives Investment Bank Analyst Rating Update","Date":1691625600000}
{"Title":"Former U.S. officials urge Congress to enhance Biden's China investment order","Date":1692144000000}
{"Title":"Super Micro Compu receives Investment Bank Analyst Rating Update","Date":1692748800000}
{"Title":"Super Micro Computer ramps 9% following NVIDIA's AI-driven results","Date":1692748800000}
{"Title":"Nvidia's forecast lifts AI stocks and Nasdaq futures","Date":1692748800000}
{"Title":"Super Micro Compu receives Investment Bank Analyst Rating Update","Date":1695081600000}
{"Title":"Dell a buy  on AI and bolstered demand: 5 big analyst picks","Date":1695081600000}
{"Title":"Oil dominates Wall Street as indexes face worst week in over a month","Date":1695340800000}
{"Title":"Super Micro Computer Introduces New All-in-One Open RAN System","Date":1695600000000}
{"Title":"Super Micro Computer trades at high, up 8.7%","Date":1696896000000}
{"Title":"Supermicro's rise in AI server market doubles share, forecasts robust growth","Date":1697500800000}
{"Title":"Supermicro Starts Shipments of NVIDIA GH200 Grace Hopper Superchip-Based Servers","Date":1697587200000}
{"Title":"Super Micro Compu receives Investment Bank Analyst Rating Update","Date":1697760000000}
{"Title":"Super Micro Computer earnings beat by $0.16, revenue topped estimates","Date":1698796800000}
{"Title":"Earnings call: Super Micro Computer Reports Q1 2024 Results, Forecasts Strong Demand for AI Platforms","Date":1698883200000}
{"Title":"Super Micro Computer lifts fiscal 2024 revenue forecast amid strong AI demand","Date":1698883200000}
{"Title":"Super Micro Compu receives Investment Bank Analyst Rating Update","Date":1698883200000}
{"Title":"Super Micro Computer Expands Global Manufacturing Footprint","Date":1699488000000}
{"Title":"Super Micro Computer Announces Upcoming NVIDIA HGX H200 and MGX Grace Hopper Platforms Featuring HBM3e Memory","Date":1699833600000}
{"Title":"Super Micro Computer to offer 2 million shares","Date":1701302400000}
{"Title":"Super Micro Computer prices 2.1M shares at $262","Date":1701388800000}
{"Title":"Super Micro Computer Extends AI and GPU Rack Scale Solutions with Support for AMD Instinct MI300 Series Accelerators","Date":1701820800000}
{"Title":"Super Micro Computer Announces Yih-Shyan (Wally) Liaw Joins Board of Directors","Date":1701993600000}
{"Title":"Super Micro Compu receives Investment Bank Analyst Rating Update","Date":1702252800000}
{"Title":"Envista cut to Sell at Goldman Sachs, CRISPR to Underperform: 4 big analyst cuts","Date":1702252800000}
{"Title":"Super Micro Computer sees strong early gains","Date":1702512000000}
{"Title":"ProPicks: January 2024 stock updates - What to buy, what to sell","Date":1704153600000}
{"Title":"What Small-Cap Stocks, Institutions And Hedge Funds Buying","Date":1704153600000}
{"Title":"Super Micro Computer Raises Second Quarter Guidance","Date":1705536000000}
{"Title":"After-hours movers: Super Micro Computer, J.B. Hunt, and more","Date":1705536000000}
{"Title":"S&P 500 notches first record high close in 2 years; chipmakers soar","Date":1705622400000}
{"Title":"Stock Market Today: S&P 500 rallies to record high as tech reigns supreme","Date":1705622400000}
{"Title":"Midday movers: Super Micro Computer, PayPal and more","Date":1705622400000}
{"Title":"Super Micro Compu receives Investment Bank Analyst Rating Update","Date":1705622400000}
{"Title":"Super Micro Computer surges after lifting guidance","Date":1705622400000}
{"Title":"Japan's Nikkei scales 34-year peak on Wall Street record","Date":1705881600000}
{"Title":"Futures higher, FAA recommends more Boeing safety checks - what's moving markets","Date":1705881600000}
{"Title":"Midday movers: Netflix gains, ASML spurs rally in chip stocks","Date":1706054400000}
{"Title":"Cautious investors trim equity holdings before inflation data, Fed meet","Date":1706227200000}
{"Title":"US equity fund withdrawals ebb to four-week low amid tech-led Wall Street rally","Date":1706227200000}
{"Title":"Super Micro Computer earnings beat by $1.08, revenue topped estimates","Date":1706486400000}
{"Title":"After-hours movers: Supermicro, F5 Networks and more","Date":1706486400000}
{"Title":"Super Micro surges as sales projection fuels AI rally","Date":1706486400000}
{"Title":"AI companies lose $190 billion in market cap after Alphabet and Microsoft report","Date":1706572800000}
{"Title":"Nasdaq ends lower ahead of big tech earnings, focus on Fed","Date":1706572800000}
{"Title":"Midday movers: GM advances, Apple declines, and more","Date":1706572800000}
{"Title":"Super Micro Compu receives Investment Bank Analyst Rating Update","Date":1706572800000}
{"Title":"Supermicro shares jump after revenue forecast raise re-ignites AI rally","Date":1706572800000}
{"Title":"Earnings call: Super Micro Computer sees 133% revenue surge in Q2","Date":1706572800000}
{"Title":"Super Micro lifts guidance after Q2 results top estimates amid AI-led demand boost","Date":1706572800000}
{"Title":"Supermicro jumps following Q2 beat, up 91% since included on ProPicks' strategy","Date":1706572800000}
{"Title":"ProPicks February 2024 stock updates: What to buy, what to sell","Date":1706745600000}
{"Title":"Super Micro Computer to Purchase Land from Caracol Property Owner","Date":1706745600000}
{"Title":"Amazon and Meta surge after results, while Apple drops","Date":1706745600000}
{"Title":"Our strategy doubled the market in January, but which stock soared 86%?","Date":1706832000000}
{"Title":"Super Micro Compu receives Investment Bank Analyst Rating Update","Date":1707696000000}
{"Title":"Super Micro shares target raised to $925 from $625, following stock price surge","Date":1707696000000}
{"Title":"Midday movers: Diamondback Energy rises, Arm goes parabolic","Date":1707696000000}
{"Title":"Super Micro Compu receives Investment Bank Analyst Rating Update","Date":1707782400000}
{"Title":"Super Micro Computer Adds to Recent Gain, Up 11%","Date":1707868800000}
{"Title":"Midday movers: Lyft rises; Airbnb, Kraft Heinz dip","Date":1707868800000}
{"Title":"Midday movers: Cisco slips; SoundHound AI, Super Micro rise","Date":1707955200000}
{"Title":"Stock Market Today:  S&P 500 rides rally in energy to close at record high","Date":1707955200000}
{"Title":"BofA sets $1040 target on Super Micro, cites AI growth","Date":1707955200000}
{"Title":"'Powerhouse in a fast-growing market': BofA starts Super Micro Computer at Buy","Date":1707955200000}
{"Title":"Super Micro Compu receives Investment Bank Analyst Rating Update","Date":1707955200000}
{"Title":"Super Micro Compu receives Investment Bank Analyst Rating Update","Date":1708041600000}
{"Title":"Super Micro Computer already discounting solid upside - Wells Fargo","Date":1708041600000}
{"Title":"Super Micro Computer Falls 13%","Date":1708041600000}
{"Title":"Midday movers: Coinbase surges; DoorDash, Roku drop","Date":1708041600000}
{"Title":"Super Micro Computer shares fall, but analysts expect the AI momentum to continue","Date":1708041600000}
{"Title":"High-flying Nvidia\u2019s earnings could test US stock market\u2019s AI dreams","Date":1708041600000}
{"Title":"Super Micro Compu receives Investment Bank Analyst Rating Update","Date":1708300800000}
{"Title":"Rosenblatt hikes Super Micro Computer PT to $1,300 amid AI computing momentum","Date":1708387200000}
{"Title":"Nvidia dethrones Tesla as Wall Street's most traded stock","Date":1708387200000}
{"Title":"Super Micro Computer Announces Proposed Offering of $1.5 Billion of Convertible Senior Notes Due 2029","Date":1708473600000}
{"Title":"Supermicro plans $1.5 billion convertible notes offering","Date":1708473600000}
{"Title":"Nvidia stock surges after results, lifts other AI shares","Date":1708473600000}
{"Title":"SMCI stock: Could Super Micro shares really add another 60%","Date":1708560000000}
{"Title":"S&P 500, Dow surge to record closing highs as Nvidia sparks AI frenzy","Date":1708560000000}
{"Title":"Midday movers: Nvidia, Moderna rise; Etsy, Rivian fall","Date":1708560000000}
{"Title":"Super Micro Computer Enters Amendment to Certain Loan and Security Agreement","Date":1708560000000}
{"Title":"AI-darling Nvidia's earnings could boost its sway over U.S. stock market","Date":1708560000000}
{"Title":"Super Micro Computer shares sink on potentially dilutive $1.5B notes offering","Date":1708646400000}
{"Title":"S&P, Dow eke out another record closing high as Nvidia momentum endures","Date":1708646400000}
{"Title":"Super Micro Computer Prices $1.5B Convertible Notes Offering","Date":1708646400000}
{"Title":"Midday movers: Nvidia erases gain; Carvana and Block rise","Date":1708646400000}
{"Title":"Stock Market Today: Dow, S&P 500 clinch record close despite pause in tech rally","Date":1708646400000}
{"Title":"5 big analyst AI moves: CMB starts Amazon at Buy; Super Micro PT lifted","Date":1708819200000}
{"Title":"Nvidia bets dominate US options market as AI fervor grows","Date":1708905600000}
{"Title":"Nvidia's Market Surge: AI Frenzy Fuels Options Trading Boom","Date":1708905600000}
{"Title":"Super Micro Computer Completes $1.725B Convertible Notes Offering","Date":1709078400000}
{"Title":"Here's another rally you may have missed while our list of AI-picked winners grows","Date":1709164800000}
{"Title":"Analysis-Wall Street hunts for more AI gold after Nvidia\u2019s soaring rally","Date":1709251200000}
{"Title":"Nvidia closes with $2 trillion valuation as Dell stokes AI rally","Date":1709251200000}
{"Title":"Analysis-High US rates, rising shares a tailwind for convertible bonds","Date":1709251200000}
{"Title":"Super Micro Computer , Deckers Outdoor to Join S&P 500","Date":1709251200000}
{"Title":"S&P 500 edges lower as investors hold their breath ahead of economic data","Date":1709510400000}
{"Title":"Super Micro shares jump as AI-bet gears up for S&P 500 entry","Date":1709510400000}
{"Title":"Stock Market Today: S&P 500 ends lower as Apple dents tech, rate-cut bets cool","Date":1709510400000}
{"Title":"Super Micro to be added to S&P 500; Is there more upside room?","Date":1709510400000}
{"Title":"Goldman Sachs starts Super Micro stock at Neutral, noting key AI partnerships","Date":1709510400000}
{"Title":"Super Micro Compu receives Investment Bank Analyst Rating Update","Date":1709510400000}
{"Title":"Midday movers: Macy's, Super Micro Computer rise; Apple, Tesla fall","Date":1709510400000}
{"Title":"Futures muted, NFPs ahead this week, Macy's takeover bid - what's moving markets","Date":1709510400000}
{"Title":"Super Micro Compu receives Investment Bank Analyst Rating Update","Date":1709683200000}
{"Title":"Super Micro stock initiated with Buy, $1,350 target by Argus","Date":1709683200000}
{"Title":"Super Micro Computer started at buy, Argus sees near and long-term growth","Date":1709683200000}
{"Title":"Up 115% last month, could this stock be the next Super Micro Computer?","Date":1709769600000}
{"Title":"Why these analysts call Super Micro the \"poster child\" of surging AI server demand","Date":1710115200000}
{"Title":"VAST Data and Supermicro Collaborate to Simplify and Accelerate AI Pipelines","Date":1710201600000}
{"Title":"BofA raises Super Micro stock price target to $1,280 on AI growth","Date":1710288000000}
{"Title":"Analysis-US stocks may not be in a bubble, but a pullback could be near","Date":1710288000000}
{"Title":"SMCI stock: BofA ups Super Micro Computer target on competitive AI advantages","Date":1710288000000}
{"Title":"Goldman lists 20 stocks where options volumes matter most, including NVDA and SMCI","Date":1710288000000}
{"Title":"These 7 AI stocks will benefit from strong demand - Bank of America","Date":1710288000000}
{"Title":"With SMCI stock through the roof, investors ask which company is next?","Date":1710288000000}
{"Title":"Super Micro Compu receives Investment Bank Analyst Rating Update","Date":1710288000000}
{"Title":"Soundhound AI stock is 'obviously' a 'pump and dump' stock - market watcher","Date":1710374400000}
{"Title":"Super Micro Computer director Chan resigns to focus on family business","Date":1710460800000}
{"Title":"Super Micro Computer Announces Resignation of Director Fred Chan","Date":1710460800000}
{"Title":"5 big analyst AI moves: AI market is not a bubble yet, says Goldman","Date":1710633600000}
{"Title":"Super Micro Computer rides AI server boom to join S&P 500","Date":1710720000000}
{"Title":"Market seesawing? No problem, these strategies keep outperforming by a wide margin","Date":1710720000000}
{"Title":"Supermicro Joins the S&P 500 Index \u201c Recognition of Remarkable Growth in Sales and Market Capitalization","Date":1710720000000}
{"Title":"Super Micro Computer stock falls after S&P 500 addition","Date":1710720000000}
{"Title":"Several stocks react to NVIDIA CEO's GTC keynote","Date":1710720000000}
{"Title":"Supermicro unveils new AI SuperCluster solutions","Date":1710720000000}
{"Title":"Supermicro unveils new AI systems with NVIDIA tech","Date":1710720000000}
{"Title":"Super Micro Computer Announces Pricing of Public Offering of Common Stock","Date":1710806400000}
{"Title":"Nvidia stock climbs as CFO says new chip to ship in 2024","Date":1710806400000}
{"Title":"Wall Street advances with Nvidia and Fed meeting in focus","Date":1710806400000}
{"Title":"Super Micro dips as AI server maker looks to sell shares","Date":1710806400000}
{"Title":"Why SMCI stock plunged 11% today","Date":1710806400000}
{"Title":"Super Micro Computer Said To Delay 2M Share Sale To After Market Close - Bloomberg","Date":1710806400000}
{"Title":"Super Micro Computer Said To Offer Shares At $900-$1,000.68 Each - Bloomberg","Date":1710806400000}
{"Title":"Morning Bid - Japan returns from upside-down world, AI fizzes","Date":1710806400000}
{"Title":"Super Micro Computer Announces Proposed 2M Share Offering","Date":1710806400000}
{"Title":"Super Micro Computer Files for 2M Share Offering","Date":1710806400000}
{"Title":"Nvidia unveils flagship AI chip, the B200, aiming to extend dominance","Date":1710806400000}
{"Title":"Super Micro Computer announces public stock offering","Date":1710806400000}
{"Title":"Missed out on NVDA, SMCI and AMD? This AI chip stock is seen as next big winner","Date":1710892800000}
{"Title":"Super Micro's shares drop after pricing stock offering at discount","Date":1710892800000}
{"Title":"Supermicro sets public offering price at $875 a share","Date":1710892800000}
{"Title":"SMCI stock drops below $900. What comes after the support break?","Date":1710892800000}
{"Title":"Analysts at Mizuho are asking if Micron is the new Nvidia Jr","Date":1710979200000}
{"Title":"Super Micro Computer Announces $2 Billion Stock Sale, Faces Initial Setback","Date":1710979200000}
{"Title":"Super Micro Compu receives Investment Bank Analyst Rating Update","Date":1711324800000}
{"Title":"SMCI stock surges 10% as JPMorgan starts at buy","Date":1711324800000}
{"Title":"Midday movers: Apple, Intel, United Airlines fall; Micron rises","Date":1711324800000}
{"Title":"Missed out on Nvidia and SMCI? Analyst says this stock is the 'hidden AI gem'","Date":1711411200000}
{"Title":"How the US stock market rocketed through the first quarter","Date":1711584000000}
{"Title":"Stock market rally safe until at least H2 2024 - HSBC","Date":1712016000000}
{"Title":"Here are our top stock picks for Q2 2024","Date":1712016000000}
{"Title":"Super Micro Computer director sells shares worth $303,000","Date":1712102400000}
{"Title":"\"Tech Titans\" ProPicks strategy outperforms in March 2024","Date":1712102400000}
{"Title":"This hedge fund is beating S&P 500 without relying on Magnificent 7; This is how","Date":1712102400000}
{"Title":"Could this Nvidia partner be a new AI winner? Evercore ISI thinks so","Date":1712102400000}
{"Title":"Investor sentiment on SMCI stock is 'mixed to negative', Goldman warns","Date":1712188800000}
{"Title":"Alset Capital Announces Investee Company Cedarcross Enters into Supply Agreement to Purchase Nvidia AI Computing Hardware from Earthmade Computer Inc., an Authorized Distributor of Super Micro Compute","Date":1712188800000}
{"Title":"These stocks are tanking - Are you still holding them?","Date":1712275200000}
{"Title":"4 chip stocks to buy as confidence in long-term outlook increases - Wolfe","Date":1712275200000}
{"Title":"Supermicro Expands Edge Compute Portfolio to Accelerate IoT and Edge AI Workloads with New Generation of Embedded Solutions","Date":1712534400000}
{"Title":"Super Micro Computer Expands Edge Compute Portfolio","Date":1712534400000}
{"Title":"SiMa.ai, CVEDIA and Supermicro Announce Collaboration to Bring Smart City Solutions to the Edge","Date":1712620800000}
{"Title":"Supermicro Announces Upcoming X14 Server Family with Future Support for the Intel \u00ae Xeon \u00ae 6 processor with Early Access Programs","Date":1712620800000}
{"Title":"Super Micro Computer : Barclays Sees Strong Earnings Print - Time to Invest?","Date":1713139200000}
{"Title":"Super Micro Compu receives Investment Bank Analyst Rating Update","Date":1713225600000}
{"Title":"SMCI stock could surge 70% from here - Loop Capital","Date":1713225600000}
{"Title":"Loop Capital lifts Super Micro stock target to by 150%","Date":1713225600000}
{"Title":"Short sellers recoup losses as rally in US stocks loses steam","Date":1713484800000}
{"Title":"Super Micro Computer now down nearly 20%","Date":1713484800000}
{"Title":"Midday movers: Netflix, Super Micro fall; Paramount Global gains","Date":1713484800000}
{"Title":"SMCI stock just dropped 13%. This could be the reason why","Date":1713484800000}
{"Title":"Supermicro to Announce Third Quarter Fiscal 2024 Earnings on April 30, 2024","Date":1713484800000}
{"Title":"Super Micro Computer Falls 6%","Date":1713484800000}
{"Title":"Super Micro stock maintains price target","Date":1713484800000}
{"Title":"Super Micro Compu receives Investment Bank Analyst Rating Update","Date":1713484800000}
{"Title":"5 big analyst AI moves: Is Wall Street underestimating Apple\u2019s AI play?","Date":1713657600000}
{"Title":"Alset Capital Inc. Investee Company Cedarcross Technologies Announces Nvidia AI Server Agreement, and Signs C$2.3 Million First H100 Server Distribution Transaction","Date":1713744000000}
{"Title":"China acquired top-end Nvidia AI chips despite recent US ban- Reuters","Date":1713830400000}
{"Title":"Exclusive-China acquired recently banned Nvidia chips in Super Micro, Dell servers, tenders show","Date":1713830400000}
{"Title":"Super Micro Compu receives Investment Bank Analyst Rating Update","Date":1713916800000}
{"Title":"KeyBanc starts coverage on Super Micro Computer stock with eyes on valuation","Date":1713916800000}
{"Title":"SMCI stock: KeyBanc starts coverage at neutral amid rich valuation","Date":1713916800000}
{"Title":"Tech sector: Which stocks will dominate the market in May? - Expert price targets","Date":1714089600000}
{"Title":"SMCI stock: Analysts preview upcoming earnings report","Date":1714348800000}
{"Title":"Super Micro misses quarterly revenue estimates as inventory up, shares down 14%","Date":1714435200000}
{"Title":"Supermicro CEO Charles Liang to Once Again Deliver CEO Keynote at COMPUTEX 2024","Date":1714435200000}
{"Title":"Super Micro Computer earnings beat by $0.85, revenue fell short of estimates","Date":1714435200000}
{"Title":"Super Micro Computer director sells over $450k in company stock","Date":1714521600000}
{"Title":"S&P 500, Nasdaq end lower after Fed rate decision, Powell press conference","Date":1714521600000}
{"Title":"AMD, Super Micro spark chip selloff as earnings miss lofty AI expectations","Date":1714521600000}
{"Title":"Super Micro CEO's spouse sells over $450k in company stock","Date":1714521600000}
{"Title":"Goldman: Pickup in stock options volumes points to stabilization in risk appetite","Date":1714521600000}
{"Title":"'The Switzerland of AI': 5 analysts discuss SMCI stock after earnings","Date":1714521600000}
{"Title":"Why Nvidia (NVDA) Shares Are Sliding Today","Date":1714521600000}
{"Title":"Earnings call: Super Micro Computer forecasts robust Q4 after record Q3","Date":1714521600000}
{"Title":"Super Micro Compu receives Investment Bank Analyst Rating Update","Date":1714521600000}
{"Title":"Midday movers: Amazon, Pfizer, Pinterest rise; AMD, Starbucks, CVS Health fall","Date":1714521600000}
{"Title":"SMCI stock tumbles as gross margin guidance overshadows Q3 beat","Date":1714521600000}
{"Title":"Supermicro Announces Participation in Upcoming Investor Events","Date":1715558400000}
{"Title":"Supermicro's Rack Scale Liquid-Cooled Solutions with the Industry's Latest Accelerators Target AI and HPC Convergence","Date":1715558400000}
{"Title":"This strategy will keep your portfolio one step ahead of the\u00a0market","Date":1715558400000}
{"Title":"Alset Capital Inc. Announces $26 Million H100 Server Contract by Investee Company Cedarcross","Date":1715817600000}
{"Title":"Hedge funds afraid to short SMCI stock, so they are shorting this one: Mizuho","Date":1716163200000}
{"Title":"Atlantic.Net Joins NVIDIA's Cloud Service Provider Program","Date":1716249600000}
{"Title":"Supermicro Introduces High-Density, Efficient, and Cost Optimized Solutions Powered by the AMD EPYC\u2122 4004 Series Processors","Date":1716249600000}
{"Title":"Nvidia earnings, Fed minutes, UK inflation - what's moving markets","Date":1716336000000}
{"Title":"Analysis-Earnings from AI-heavyweight Nvidia to test US stocks\u2019 record run","Date":1716336000000}
{"Title":"Nvidia's strong forecast lifts shares of AI chipmakers","Date":1716336000000}
{"Title":"JPM: Nvidia read-through positive for Dell, Super Micro, HP Enterprise, concerns for Arista, Cisco","Date":1716422400000}
{"Title":"SuperMicro Computer, MicroStrategy set to join Russell 1000","Date":1716595200000}
{"Title":"Alset Capital Inc. Provides Corporate and Operational Update","Date":1716940800000}
{"Title":"Dell earnings preview: This number is all that matters says Bernstein","Date":1716940800000}
{"Title":"These are some of the top-performing trades so far this year","Date":1716940800000}
{"Title":"Supermicro Liquid-Cooled AI SuperClusters Will Power Large-Scale AI Data Center in Japan","Date":1717286400000}
{"Title":"Super Micro Computer director sells $419k in stock","Date":1717372800000}
{"Title":"Supermicro Unveils New X14 AI, Rackmount, Multi-Node, and Edge Server Families Based on Intel \u00ae Xeon \u00ae 6 Processors with E-cores and Soon, P-cores Systems With Liquid Cooling","Date":1717372800000}
{"Title":"Super Micro Computer Unveils New X14 AI","Date":1717459200000}
{"Title":"Supermicro Introduces Rack Scale Plug-and-Play Liquid-Cooled AI SuperClusters for NVIDIA Blackwell and NVIDIA HGX H100\/H200 - Radical Innovations in the AI Era to Make Liquid-Cooling Free with a Bonus","Date":1717459200000}
{"Title":"Super Micro Computer gains after introducing liquid-cooled AI superclusters","Date":1717545600000}
{"Title":"Super Micro director Fairfax sells $240,600 in company stock","Date":1717545600000}
{"Title":"Nvidia overtakes Apple as No. 2 most valuable company","Date":1717632000000}
{"Title":"Barclays remains positive on SMCI stock and negative on Dell. Here's why","Date":1717632000000}
{"Title":"Mizuho:  DC infrastructure power efficiency be a bottleneck for AI server growth","Date":1718064000000}
{"Title":"Super Micro Computer surges 5% intra-day","Date":1718236800000}
{"Title":"U.S. stocks mixed at close of trade; Dow Jones Industrial Average down 0.17%","Date":1718236800000}
{"Title":"Supermicro Adding 3 New Manufacturing Facilities in Silicon Valley and Globally to Support the Growth of AI and Enterprise Rack Scale Liquid-Cooled Solutions","Date":1718582400000}
{"Title":"Super Micro Computer gains after adding 3 new manufacturing facilities","Date":1718668800000}
{"Title":"AI fever drives Nvidia\u2019s rise to world\u2019s most valuable company","Date":1718755200000}
{"Title":"Dell, Nvidia and SMCI collaborate to power Musk's Grok AI factory","Date":1718841600000}
{"Title":"Nvidia, Accenture and KB Home rise premarket;  Trump Media, Winnebago fall","Date":1718841600000}
{"Title":"Nvidia loses top spot to Microsoft after 3% drop","Date":1718841600000}
{"Title":"S&P, Nasdaq end lower as Nvidia drags the tech sector for second day","Date":1718928000000}
{"Title":"U.S. stocks mixed at close of trade; Dow Jones Industrial Average up 0.67%","Date":1719187200000}
{"Title":"These stocks are outperforming Nvidia in June","Date":1719187200000}
{"Title":"AI stocks to leave big impact on Russell reconstitution","Date":1719360000000}
{"Title":"U.S. stocks higher at close of trade; Dow Jones Industrial Average up 0.09%","Date":1719446400000}
{"Title":"U.S. stocks lower at close of trade; Dow Jones Industrial Average down 0.12%","Date":1719532800000}
{"Title":"ProPicks \"Beat the S&P 500\" soars with 24.91% Adobe gain, outpacing benchmarks","Date":1719792000000}
{"Title":"Super Micro Computer CEO posts picture with Elon Musk at AI data center","Date":1719878400000}
{"Title":"These stocks are getting a head start in July","Date":1720137600000}
{"Title":"U.S. stocks mixed at close of trade; Dow Jones Industrial Average down 0.08%","Date":1720396800000}
{"Title":"These stocks are rallying big time in July - Are they in your portfolio?","Date":1720483200000}
{"Title":"Super Micro Compu receives Investment Bank Analyst Rating Update","Date":1720569600000}
{"Title":"Nomura sees limited upside for SMCI stock, cuts rating","Date":1720569600000}
{"Title":"This is when Super Micro Computer could preannounce results: Wells Fargo","Date":1720569600000}
{"Title":"This stock is up 5% after better-than-expected CPI reading","Date":1720656000000}
{"Title":"Super Micro Compu receives Investment Bank Analyst Rating Update","Date":1720656000000}
{"Title":"Barclays maintains $1000 target on Super Micro Computer","Date":1720656000000}
{"Title":"5 big analyst AI moves: Tesla and SMCI stocks downgraded","Date":1720915200000}
{"Title":"Super Micro Computer Joins the Nasdaq 100 Index","Date":1721001600000}
{"Title":"Supermicro joins Nasdaq 100 Index amid growth","Date":1721001600000}
{"Title":"SMCI stock climbs ahead of Nasdaq-100 inclusion","Date":1721001600000}
{"Title":"Super Micro Computer is in discussions with one or more financial institutions regarding a potential senior revolving credit facility","Date":1721606400000}
{"Title":"Super Micro Computer to Announce Fourth Quarter and Full Year Fiscal Year 2024 Financial Results on August 6, 2024","Date":1721779200000}
{"Title":"Why Super Micro Computer (SMCI) stock just dropped","Date":1721779200000}
{"Title":"Super Micro sets Q4 and full year earnings call for August","Date":1721779200000}
{"Title":"VCI Global Enters Into AI Computing Alliance (AICA) Led by Enlight Corporation and Supermicro","Date":1721952000000}
{"Title":"VCI Global joins AI Computing Alliance, to build center in Malaysia","Date":1721952000000}
{"Title":"Super Micro Computer Launches Plug-and-Play SuperCluster for NVIDIA Omniverse","Date":1722470400000}
{"Title":"Supermicro unveils scalable AI infrastructure","Date":1722470400000}
{"Title":"Take Five: Global rate cuts? We're halfway there","Date":1722556800000}
{"Title":"Top 5 things to watch in markets in the week ahead","Date":1722729600000}
{"Title":"Magnificent Seven set to shed $800 billion in value","Date":1722816000000}
{"Title":"U.S. chips names open sharply lower amid broad market losses","Date":1722816000000}
{"Title":"Broadcom and SMCI stocks tumble amid market decline","Date":1722816000000}
{"Title":"Super Micro Compu receives Investment Bank Analyst Rating Update","Date":1722816000000}
{"Title":"Take Five: Global rate cuts? We're halfway there","Date":1722816000000}
{"Title":"JPMorgan cuts Super Micro stock target price on AI concerns","Date":1722816000000}
{"Title":"US futures, Nikkei rebound, Google's case - what's moving markets","Date":1722902400000}
{"Title":"SMCI earnings call will be under microscope for Nvidia read through","Date":1722902400000}
{"Title":"Super Micro Computer plans 10-for-1 forward split","Date":1722902400000}
{"Title":"Super Micro Computer earnings missed by $1.85, revenue was in line with estimates","Date":1722902400000}
{"Title":"After-hours movers: Airbnb, Super Micro, Lumen, Upstart and more","Date":1722902400000}
{"Title":"Supermicro Announces Fourth Quarter and Full Fiscal Year 2024 Financial Results","Date":1722902400000}
{"Title":"Nasdaq ends down 1% as tech shares fall; Treasury auction weak","Date":1722988800000}
{"Title":"U.S. stocks lower at close of trade; Dow Jones Industrial Average down 0.60%","Date":1722988800000}
{"Title":"Earnings call: Super Micro Computer sees record revenue in AI-driven growth","Date":1722988800000}
{"Title":"High-flying Super Micro slides as margin squeeze clouds upbeat sales forecast","Date":1722988800000}
{"Title":"SMCI shares tumble 12% on Q4 margin miss; BofA downgrades to Neutral","Date":1722988800000}
{"Title":"BofA cuts SMCI stock rating to Neutral amid margin headwinds","Date":1722988800000}
{"Title":"Stock Market Today: S&P 500 closes lower as rebound fades","Date":1722988800000}
{"Title":"Mixed implications for Dell from SMCI results: Citi","Date":1722988800000}
{"Title":"Super Micro Compu receives Investment Bank Analyst Rating Update","Date":1722988800000}
{"Title":"Morning Bid: BOJ eases market migraine, Super Micro aches","Date":1722988800000}
{"Title":"Midday movers: Super Micro Computer, Airbnb and Lyft fall; Shopify rises","Date":1722988800000}
{"Title":"SMCI earnings: Here's how analysts reacted","Date":1722988800000}
{"Title":"Media Alert: Supermicro Announces Open Storage Summit '24 -- Starts August 13","Date":1723075200000}
{"Title":"Global equities to stage a near-term rebound: UBS","Date":1723161600000}
{"Title":"5 big analyst AI moves: Intel, SMCI hit by downgrades; Micron still top semis pick","Date":1723334400000}
{"Title":"Supermicro Announces Participation in Upcoming Investor Events","Date":1723420800000}
{"Title":"Hazeltree report shows SMCI ahead of Tesla as most shorted security in July","Date":1723766400000}
{"Title":"AI server providers fall as AMD acquries ZT Systems in massive deal","Date":1724025600000}
{"Title":"Super Micro Computer : Susie Giordano Joins Supermicro\u2019s Board of Directors","Date":1724025600000}
{"Title":"Supermicro adds Susie Giordano to its board","Date":1724025600000}
{"Title":"Midday movers: PDD Holdings, NVIDIA fall; Xpeng gains","Date":1724630400000}
{"Title":"U.S. stocks mixed at close of trade; Dow Jones Industrial Average up 0.16%","Date":1724630400000}
{"Title":"These stocks 'are all expected to prosper' if Trump wins election: Navellier","Date":1724716800000}
{"Title":"Super Micro Computer mentioned cautiously at Hindenburg","Date":1724716800000}
{"Title":"Super Micro (SMCI) stock slides after short seller Hindenburg attack","Date":1724716800000}
{"Title":"Hindenburg takes aim at AI server maker Super Micro with short position","Date":1724716800000}
{"Title":"Rosenblatt maintains $1,300 target on Super Micro amid 10K delay","Date":1724803200000}
{"Title":"Super Micro shares slammed following delay in annual filing","Date":1724803200000}
{"Title":"Supermicro previews new X14 servers with Intel CPUs","Date":1724803200000}
{"Title":"Super Micro Computer Previews New Max Performance Intel-based X14 Servers for AI, HPC, and Critical Enterprise Workloads","Date":1724803200000}
{"Title":"Super Micro Computer (SMCI) stock plunge overdone says Rosenblatt","Date":1724803200000}
{"Title":"Super Micro Computer to Delay Form 10-K Filing for Fiscal Year 2024","Date":1724803200000}
{"Title":"CFRA cuts Super Micro stock target on Hindenburg report","Date":1724803200000}
{"Title":"Super Micro stock target lowered by Wells Fargo, reflecting a 42% downside potential","Date":1724803200000}
{"Title":"Super Micro Compu receives Investment Bank Analyst Rating Update","Date":1724803200000}
{"Title":"Super Micro delays annual financial report filing","Date":1724803200000}
{"Title":"SMCI stock 'in penalty box' after 10-K delay: Barclays","Date":1724889600000}
{"Title":"Dell shares rise as AI server demand boosts results, forecasts","Date":1724976000000}
{"Title":"Super Micro Computer to Delay 10-K","Date":1724976000000}
{"Title":"U.S. stocks higher at close of trade; Dow Jones Industrial Average up 0.55%","Date":1724976000000}
{"Title":"Super Micro issues customer and partner letter","Date":1725321600000}
{"Title":"AI server maker Super Micro denies short-seller Hindenburg's claims","Date":1725321600000}
{"Title":"Super Micro Computer issues letter to its Customers and Partners","Date":1725321600000}
{"Title":"SMCI issues letter to customers and partners: CEO has 'strong' confidence in teams","Date":1725321600000}
{"Title":"Super Micro Compu receives Investment Bank Analyst Rating Update","Date":1725408000000}
{"Title":"Barclays downgrades Super Micro Computer on AI server concerns and market share loss","Date":1725408000000}
{"Title":"Super Micro Computer shares tumble on Barclays downgrade","Date":1725408000000}
{"Title":"JPMorgan downgrades Super Micro stock as regulatory uncertainty looms","Date":1725580800000}
{"Title":"Super Micro Computer stock slips as JPMorgan cuts rating on uncertainty","Date":1725580800000}
{"Title":"Midday movers: Broadcom, Mobileye shares fall; Samsara rises","Date":1725580800000}
{"Title":"5 big analyst AI moves: AI stocks not in bubble; SMCI downgraded","Date":1725753600000}
{"Title":"ATTENTION NASDAQ: SMCI INVESTORS: Contact Berger Montague About a Super Micro Computer Class Action Lawsuit","Date":1725840000000}
{"Title":"Super Micro Computer Mentioned as Long at GlassHouse Research","Date":1725840000000}
{"Title":"INVESTOR REMINDER: Berger Montague Notifies Super Micro Computer (NASDAQ: SMCI) Investors of a Class Action Lawsuit and Deadline","Date":1726444800000}
{"Title":"Super Micro Compu receives Investment Bank Analyst Rating Update","Date":1726444800000}
{"Title":"Mizuho starts Super Micro Computer at Neutral amid profitability risks","Date":1726444800000}
{"Title":"Mizuho initiates coverage on Dell, SMCI amid AI boom","Date":1726531200000}
{"Title":"Needham initiates Buy on Super Micro shares, bullish on AI-driven growth opportunities","Date":1726617600000}
{"Title":"This embattled stock is 'the coolest kid in AI town' says Needham","Date":1726617600000}
{"Title":"Super Micro Compu receives Investment Bank Analyst Rating Update","Date":1726617600000}
{"Title":"General Mills edges lower premarket; US Steel climbs","Date":1726617600000}
{"Title":"Supermicro's New Multi-Node Liquid Cooled Architecture with Maximum Performance Density Purpose-Built for HPC at Scale","Date":1726704000000}
{"Title":"Supermicro unveils high-density FlexTwin servers for HPC","Date":1726704000000}
{"Title":"CLASS ACTION REMINDER: Berger Montague Advises Super Micro Computer (NASDAQ: SMCI) Investors to Inquire About a Securities Fraud Lawsuit by October 29, 2024","Date":1726704000000}
{"Title":"Super Micro Computer Investors: October 29, 2024 Filing Deadline in Securities Class Action \u201c Contact Lieff Cabraser","Date":1726790400000}
{"Title":"Super Micro Computer, Inc. Announces Receipt of Non-Compliance Letter from Nasdaq","Date":1726790400000}
{"Title":"Is Super Micro (SMCI) a $1,000 stock? Wall Street analyst discusses","Date":1727049600000}
{"Title":"SUPER MICRO COMPUTER (NASDAQ: SMCI) INVESTOR ALERT: Berger Montague Advises Investors to Inquire About a Securities Fraud Class Action","Date":1727049600000}
{"Title":"Super Micro Compu receives Investment Bank Analyst Rating Update","Date":1727049600000}
{"Title":"Loop Capital cuts Super Micro stock target, retains buy rating","Date":1727049600000}
{"Title":"Supermicro Adds New Max-Performance Intel-Based X14 Servers, Delivering the Industry's Broadest Range of Workload-Optimized Systems for AI, HPC, Cloud, and Edge","Date":1727136000000}
{"Title":"Supermicro expands X14 server lineup with new Intel CPUs","Date":1727136000000}
{"Title":"Justice Department Probes Server Maker Super Micro -- WSJ","Date":1727308800000}
{"Title":"Super Micro Computer Halted on Circuit Breaker, Down 4.75%","Date":1727308800000}
{"Title":"Super Micro Computer probed by DoJ - WSJ","Date":1727308800000}
{"Title":"US Justice Department probes Super Micro Computer, WSJ reports","Date":1727308800000}
{"Title":"Stock Market Today: S&P 500 clinches record closing high on Micron-led rally","Date":1727308800000}
{"Title":"Super Micro announces 10-for-1 stock split","Date":1727308800000}
{"Title":"Super Micro announces stock split, loan amendments","Date":1727654400000}
{"Title":"NASDAQ: SMCI DEADLINE REMINDER: Berger Montague Reminds Super Micro Computer (NASDAQ: SMCI) Investors of Important Class Action Lawsuit Deadline","Date":1727654400000}
{"Title":"Loop Capital defends Super Micro (SMCI), says it remains 'a $1,000 stock'","Date":1727740800000}
{"Title":"U.S. stocks higher at close of trade; Dow Jones Industrial Average up 0.09%","Date":1727827200000}
{"Title":"Super Micro Compu receives Investment Bank Analyst Rating Update","Date":1727827200000}
{"Title":"5 big analyst AI moves: JPMorgan sees significant downside risk in Tesla stock","Date":1728172800000}
{"Title":"Super Micro Computer Currently Shipping Over 100,000 GPUs Per Quarter","Date":1728259200000}
{"Title":"Supermicro introduces full-scale liquid cooling for data centers","Date":1728259200000}
{"Title":"Super Micro Computer Extends Gain, Up 13%","Date":1728259200000}
{"Title":"SMCI currently shipping over 100,000 GPUs per quarter: Stock jumps","Date":1728259200000}
{"Title":"Super Micro shares surge as AI boom drives 100,000 quarterly GPU shipments","Date":1728259200000}
{"Title":"Honeywell, Super Micro Computer rise premarket; PepsiCo slips","Date":1728345600000}
{"Title":"Super Micro Computer Introduces New Versatile System Design for AI Delivering Optimization and Flexibility at the Edge","Date":1728345600000}
{"Title":"Supermicro launches AI-optimized server platform","Date":1728345600000}
{"Title":"Super Micro Computer, Inc. Investor Alert (NASDAQ: SMCI): Schubert Jonckheer & Kolbe LLP Investigating Potential Shareholder Claims Amid U.S. Justice Department Probe and Delayed 10-K Annual Repor","Date":1728432000000}
{"Title":"Super Micro Computer Introduces New Servers and GPU Accelerated Systems with AMD EPYC 9005 Series CPUs and AMD Instinct MI325X GPUs","Date":1728518400000}
{"Title":"Supermicro unveils H14 servers for AI data centers","Date":1728518400000}
{"Title":"Here is what analysts had to say after AMD's AI event","Date":1728604800000}
{"Title":"Investing.com stocks of the week","Date":1728691200000}
{"Title":"NVIDIA, other AI stocks fall on weak net bookings from ASML","Date":1728950400000}
{"Title":"Supermicro Adds New Petascale JBOF All-Flash Storage Solution Integrating NVIDIA BlueField-3 DPU for AI Data Pipeline Acceleration","Date":1728950400000}
{"Title":"Supermicro unveils AI-optimized storage system","Date":1728950400000}
{"Title":"Supermicro's Liquid-Cooled SuperClusters for AI Data Centers Powered by NVIDIA GB200 NVL72 and NVIDIA HGX B200 Systems, Deliver a New Paradigm of Energy-Efficient Exascale Computing","Date":1728950400000}
{"Title":"Supermicro boosts AI data centers with liquid cooling","Date":1728950400000}
{"Title":"Super Micro Computer on watch as Dell announces advanced cooling technology","Date":1728950400000}
{"Title":"DEADLINE APPROACHING: Berger Montague Advises Super Micro Computer (NASDAQ: SMCI) Investors to Inquire About a Securities Fraud Class Action by October 29, 2024","Date":1729209600000}
{"Title":"Super Micro Computer (SMCI) Faces Multiple Legal Fronts Amid Financial Allegations - Hagens Berman","Date":1729728000000}
{"Title":"DEADLINE APPROACHING: Berger Montague Advises Super Micro Computer (NASDAQ: SMCI) Investors to Inquire About a Securities Fraud Class Action by October 29, 2024","Date":1729814400000}
{"Title":"DEADLINE THIS WEEK: Berger Montague Advises Super Micro Computer (NASDAQ: SMCI) Investors to Contact the Firm Before October 29, 2024","Date":1729987200000}
{"Title":"Mizuho maintains neutral rating on Super Micro shares, eyes delisting risk","Date":1730246400000}
{"Title":"Stock market today: S&P500 slips amid rising yields easing Alphabet rally","Date":1730246400000}
{"Title":"CORRECTING and REPLACING Supermicro Schedules Conference Call and Webcast for First Quarter Fiscal 2025 Business Update","Date":1730246400000}
{"Title":"Super Micro Compu receives Investment Bank Analyst Rating Update","Date":1730246400000}
{"Title":"Super Micro Computer says Ernst & Young resigns as auditor, shares tank","Date":1730246400000}
{"Title":"Super Micro Computer halted on volatility, last $37.42","Date":1730246400000}
{"Title":"Super Micro Computer stock plunges as accountant resigns","Date":1730246400000}
{"Title":"Super Micro Computer sinks as Ernst & Young resigns as auditor","Date":1730246400000}
{"Title":"Supermicro Schedules Conference Call and Webcast for First Quarter Fiscal 2025 Business Update","Date":1730246400000}
{"Title":"Super Micro Computer's Certifying Accountant Ernst & Young Resigns","Date":1730246400000}
{"Title":"Buy Dell stock on SMCI's auditor woes - analyst","Date":1730332800000}
{"Title":"Super Micro shares downgraded to hold amid accounting concerns","Date":1730332800000}
{"Title":"Super Micro shares downgraded to Hold amid accounting concerns","Date":1730332800000}
{"Title":"Microsoft, Meta report; Samsung's chip unit disappoints - what's moving markets","Date":1730332800000}
{"Title":"Rosenblatt suspends SMCI rating amid 'financial uncertainty'; shares fall again","Date":1730332800000}
{"Title":"Morning Bid: Megacaps spooked, world bonds on edge","Date":1730332800000}
{"Title":"Super Micro Compu receives Investment Bank Analyst Rating Update","Date":1730332800000}
{"Title":"Can NVIDIA's stock stay out of the SMCI fire?","Date":1730419200000}
{"Title":"U.S. stocks higher at close of trade; Dow Jones Industrial Average up 0.69%","Date":1730419200000}
{"Title":"5 big analyst AI moves: SMCI rating suspended, ARM stock downgraded","Date":1730592000000}
{"Title":"Top 5 things to watch in markets in the week ahead","Date":1730592000000}
{"Title":"Nvidia said to be routing orders away from Super Micro amid accounting woes","Date":1730678400000}
{"Title":"Super Micro Compu receives Investment Bank Analyst Rating Update","Date":1730678400000}
{"Title":"SMCI stock touches 52-week low at $24.87 amid market shifts","Date":1730678400000}
{"Title":"Investing.com's stocks of the week","Date":1730678400000}
{"Title":"US election looms large; earnings, Fed decision this week - what's moving markets","Date":1730678400000}
{"Title":"Dow Jones, Nasdaq, S&P 500 weekly preview: Neck-and-neck election nears conclusion","Date":1730678400000}
{"Title":"After-hours movers: Super Micro Computer, Exact Sciences, Trump Media & Technology","Date":1730764800000}
{"Title":"Super Micro may have to dump NVIDIA Blackwell to survive \u2013 analyst","Date":1730764800000}
{"Title":"Super Micro Computer Revises Prelim Q1 Guidance, Issues Update from the Independent Special Committee","Date":1730764800000}
{"Title":"Super Micro reports preliminary Q1 fiscal 2025 results","Date":1730764800000}
{"Title":"Super Micro shares fall as server maker misses sales targets, annual filing uncertain","Date":1730764800000}
{"Title":"Super Micro slumps as weak forecast, annual report uncertainty fuel investor angst","Date":1730851200000}
{"Title":"SMCI cut to sell at JPMorgan","Date":1730851200000}
{"Title":"Barclays cuts Super Micro stock target on compliance concerns","Date":1730851200000}
{"Title":"Super Micro shares target cut on revenue miss, risks","Date":1730851200000}
{"Title":"Super Micro Compu receives Investment Bank Analyst Rating Update","Date":1730851200000}
{"Title":"Earnings call: Super Micro sees robust growth in Q1 FY'25","Date":1730851200000}
{"Title":"Super Micro shares hold as Needham awaits new auditor","Date":1730851200000}
{"Title":"Trump Media, Tesla, Citigroup rise premarket; Super Micro falls","Date":1730851200000}
{"Title":"Super Micro slumps 20% on guidance cut; says recent probe shows no fraud evidence","Date":1730851200000}
{"Title":"Mizuho halts Super Micro stock rating over financial clarity issues","Date":1730851200000}
{"Title":"5 big analyst AI moves: Nvidia top November pick, SMCI downgraded","Date":1731196800000}
{"Title":"Are Super Micro's recent struggles good for Dell and HPE? Bernstein weighs in","Date":1731369600000}
{"Title":"U.S. stocks mixed at close of trade; Dow Jones Industrial Average up 0.11%","Date":1731456000000}
{"Title":"Super Micro Computer delays 10-Q filling","Date":1731456000000}
{"Title":"Super Micro Computer stock falls after delaying 10-Q filling","Date":1731456000000}
{"Title":"SMCI stock touches 52-week low at $17.94 amid market challenges","Date":1731542400000}
{"Title":"Tesla, Spirit Airlines and CVS Health rise premarket; Nvidia falls","Date":1731888000000}
{"Title":"SMCI stock jumps on report it plans to submit plan to retain Nasdaq listing","Date":1731888000000}
{"Title":"Super Micro Computer Delivers Direct-Liquid-Optimized NVIDIA Blackwell Solutions","Date":1731888000000}
{"Title":"Supermicro expands AI compute density with new systems","Date":1731888000000}
{"Title":"Super Micro Computer on watch after stock quickly loses 10%","Date":1731888000000}
{"Title":"Super Micro Computer Announces Appointment of BDO USA as Independent Auditor and Filing of Compliance Plan with Nasdaq","Date":1731888000000}
{"Title":"After-hours movers: Super Micro Computer, Bakkt Holdings, Incyte, and more","Date":1731888000000}
{"Title":"Super Micro appoints BDO as new independent auditor","Date":1731888000000}
{"Title":"Super Micro Computer names BDO as auditor, files Nasdaq compliance plan","Date":1731888000000}
{"Title":"S&P 500, Nasdaq end up with Nvidia; Walmart hits record after forecast","Date":1731974400000}
{"Title":"U.S. stocks mixed at close of trade; Dow Jones Industrial Average down 0.28%","Date":1731974400000}
{"Title":"Super Micro appoints BDO USA as new auditor amid compliance push","Date":1731974400000}
{"Title":"Super Micro Computer Showcases Largest Portfolio of HPC-Optimized Multi-Node Systems","Date":1731974400000}
{"Title":"Microsoft-backed startup d-Matrix launches first AI chip","Date":1731974400000}
{"Title":"Walmart, Super Micro Computer, BioNTech rise premarket; Lowe's falls","Date":1731974400000}
{"Title":"Super Micro shares soar over 30% after naming new auditor","Date":1731974400000}
{"Title":"Supermicro Showcases Largest Portfolio of HPC-Optimized Multi-Node Systems at SuperComputing 2024","Date":1731974400000}
{"Title":"SMCI 'just too important a player' in AI space to be delisted, says analyst","Date":1731974400000}
{"Title":"Hedge funds cut exposure to Semis, rotate into Cyclicals, says Goldman","Date":1732060800000}
{"Title":"Super Micro Computer Announces Nasdaq Non-Compliance Update","Date":1732060800000}
{"Title":"Super Micro Computer Inc. Nasdaq Non-Compliance Update","Date":1732060800000}
{"Title":"Nvidia results positive for Dell, HPE, SuperMicro: Citi","Date":1732147200000}
{"Title":"Super Micro Computer Rapidly Climbs to $29 Handle, +13% Today","Date":1732147200000}
{"Title":"U.S. stocks higher at close of trade; Dow Jones Industrial Average up 1.06%","Date":1732147200000}
{"Title":"AbbVie, Nvidia Lead Friday's Market Cap Stock Movers","Date":1732233600000}
{"Title":"U.S. stocks higher at close of trade; Dow Jones Industrial Average up 0.97%","Date":1732233600000}
{"Title":"Investing.com stocks of the week","Date":1732320000000}
{"Title":"5 big analyst AI moves: Nvidia earnings good for TSMC, Apple gets new bull-case PT","Date":1732406400000}
{"Title":"Super Micro extends last week's gain, wounding short sellers","Date":1732492800000}
{"Title":"Super Micro pays off bank loans, ends agreements","Date":1732579200000}
{"Title":"Super Micro Computer prepaid in full and terminated its obligations under loan agreements with Bank of America","Date":1732579200000}
{"Title":"U.S. stocks higher at close of trade; Dow Jones Industrial Average up 0.28%","Date":1732579200000}
{"Title":"Super Micro Computer Falls 18%","Date":1732838400000}
{"Title":"These are the top 10 stock buys in November on Robinhood UK","Date":1733097600000}
{"Title":"Super Micro Computer Announces Completion of Review by Independent Special Committee","Date":1733097600000}
{"Title":"Super Micro exonerated by internal review, no financial restatements","Date":1733097600000}
{"Title":"SMCI stock surges following review, announces plans for new CFO","Date":1733097600000}
{"Title":"U.S. stocks mixed at close of trade; Dow Jones Industrial Average down 0.29%","Date":1733097600000}
{"Title":"SMCI: JPMorgan says watch these two points after special committee review","Date":1733097600000}
{"Title":"Super Micro stock continues to rise as probe finds no management misconduct","Date":1733184000000}
{"Title":"Super Micro Computer Quickly Erases Gain, Falls Over 5%","Date":1733184000000}
{"Title":"Musk's xAI to expand supercomputer 10-fold to over one million GPUs","Date":1733356800000}
{"Title":"Super Micro Computer gets extension to file delayed annual report","Date":1733443200000}
{"Title":"Super Micro Computer granted NASDAQ listing extension","Date":1733443200000}
{"Title":"Super Micro stock jumps after Nasdaq grants filing extension","Date":1733443200000}
{"Title":"Super Micro Computer Inc. Announces Receipt of Extension from Nasdaq Stock Market","Date":1733443200000}
{"Title":"Super Micro Computer stock jumps after Nasdaq extension on listing rules","Date":1733702400000}
{"Title":"Lynx Equity increases Super Micro shares target on NASDAQ extension","Date":1733702400000}
{"Title":"U.S. stocks lower at close of trade; Dow Jones Industrial Average down 0.35%","Date":1733788800000}
{"Title":"Super Micro confident Nasdaq delisting would not happen amid audit scandal","Date":1733788800000}
{"Title":"Super Micro CEO confident stock will not be delisted","Date":1733788800000}
{"Title":"Palantir , Microstrategy, Inc. Likely to Join Nasdaq 100 as Moderna Exists - Bloomberg Intelligence","Date":1733788800000}
{"Title":"Super Micro Computer CEO Says He Is Confident The Company's Stock Won't Be Delisted From Nasdaq - Reuters","Date":1733788800000}
{"Title":"Super Micro Computer Quickly Falls to Low, Down 4.7%","Date":1733788800000}
{"Title":"Super Micro shares drop 8% amid Nasdaq 100 changes","Date":1733788800000}
{"Title":"Super Micro Computer Is Said To Tap Evercore To Raise Capital - Bloomberg","Date":1734048000000}
{"Title":"Super Micro enlists Evercore to explore capital raising options, Bloomberg reports","Date":1734048000000}
{"Title":"Palantir , MicroStrategy , and Axon to join NASDAQ 100","Date":1734048000000}
{"Title":"Super Micro Computer's SWOT analysis: navigating turbulent waters in AI server stock","Date":1734220800000}
{"Title":"MicroStrategy stock surges on Nasdaq-100 inclusion announcement","Date":1734307200000}
{"Title":"Super Micro to exit Nasdaq-100, shares plunge 15% pre-open Monday","Date":1734307200000}
{"Title":"U.S. stocks mixed at close of trade; Dow Jones Industrial Average down 0.25%","Date":1734307200000}
{"Title":"Nasdaq closes at record as investors prepare for Fed rate decision","Date":1734307200000}
{"Title":"Super Micro Compu receives Investment Bank Analyst Rating Update","Date":1734393600000}
{"Title":"U.S. Prompts Nvidia, Supermicro Probe Into How Chips Ended Up in China - The Information","Date":1734566400000}
{"Title":"U.S. pressures Nvidia, SMCI to probe AI chip smuggling to China - The Information","Date":1734566400000}
{"Title":"US prompts Nvidia probe into how chips ended up in China, The Information reports","Date":1734566400000}
